adafruit_jwt.py
adafruit_circuitpython_jwt-1.2.23.dist-info/licenses/LICENSE
adafruit_circuitpython_jwt-1.2.23.dist-info/METADATA
adafruit_circuitpython_jwt-1.2.23.dist-info/WHEEL
adafruit_circuitpython_jwt-1.2.23.dist-info/top_level.txt
adafruit_circuitpython_jwt-1.2.23.dist-info/RECORD
