Metadata-Version: 2.4
Name: adafruit-circuitpython-jwt
Version: 1.2.23
Summary: JSON Web Token Authentication 
Author-email: Adafruit Industries <circuitpython@adafruit.com>
License: MIT
Project-URL: Homepage, https://github.com/adafruit/Adafruit_CircuitPython_JWT
Keywords: adafruit,blinka,circuitpython,micropython,jwt,jwt,,json,,token,,authentication
Classifier: Intended Audience :: Developers
Classifier: Topic :: Software Development :: Libraries
Classifier: Topic :: Software Development :: Embedded Systems
Classifier: Topic :: System :: Hardware
Classifier: License :: OSI Approved :: MIT License
Classifier: Programming Language :: Python :: 3
License-File: LICENSE
Requires-Dist: Adafruit-Blinka
Requires-Dist: adafruit-circuitpython-binascii
Requires-Dist: adafruit-circuitpython-rsa
Requires-Dist: adafruit-circuitpython-typing
Provides-Extra: optional
Requires-Dist: rsa; extra == "optional"
Dynamic: license-file
